mcp_server_vefaas_sandbox/__init__.py
mcp_server_vefaas_sandbox/server.py
vefaas_sand_box_mcp_server-0.1.0.dist-info/METADATA
vefaas_sand_box_mcp_server-0.1.0.dist-info/WHEEL
vefaas_sand_box_mcp_server-0.1.0.dist-info/entry_points.txt
vefaas_sand_box_mcp_server-0.1.0.dist-info/top_level.txt
vefaas_sand_box_mcp_server-0.1.0.dist-info/RECORD
