Metadata-Version: 2.4
Name: vefaas-sand-box-mcp-server
Version: 0.1.0
Summary: Add your description here
Requires-Python: >=3.13
Requires-Dist: mcp>=1.6.0
